apistub/__init__.py
apistub/__main__.py
apistub/_apiview.py
apistub/_diagnostic.py
apistub/_metadata_map.py
apistub/_node_index.py
apistub/_stub_generator.py
apistub/_token.py
apistub/_token_kind.py
apistub/_version.py
apistub/pylintrc
apistub/nodes/__init__.py
apistub/nodes/_annotation_parser.py
apistub/nodes/_argtype.py
apistub/nodes/_astroid_parser.py
apistub/nodes/_base_node.py
apistub/nodes/_class_node.py
apistub/nodes/_data_class_node.py
apistub/nodes/_docstring_parser.py
apistub/nodes/_enum_node.py
apistub/nodes/_function_node.py
apistub/nodes/_key_node.py
apistub/nodes/_module_node.py
apistub/nodes/_property_node.py
apistub/nodes/_pylint_parser.py
apistub/nodes/_variable_node.py
tests/__init__.py
tests/_test_util.py
tests/apiview_test.py
tests/class_parsing_test.py
tests/dataclass_parsing_test.py
tests/docstring_parser_test.py
tests/function_parsing_test.py
apiview_stub_generator-0.3.7.dist-info/METADATA
apiview_stub_generator-0.3.7.dist-info/WHEEL
apiview_stub_generator-0.3.7.dist-info/entry_points.txt
apiview_stub_generator-0.3.7.dist-info/top_level.txt
apiview_stub_generator-0.3.7.dist-info/RECORD
