Metadata-Version: 2.1
Name: apiview-stub-generator
Version: 0.3.7
Summary: A stub generator for published APIs, variables and properties in a package
Home-page: https://github.com/Azure/azure-sdk-tools/
Author: Microsoft Corporation
Author-email: azuresdkengsysadmins@microsoft.com
License: MIT License
Classifier: Development Status :: 3 - Alpha
Classifier: Programming Language :: Python
Classifier: Programming Language :: Python :: 3.7
Classifier: Programming Language :: Python :: 3.8
Classifier: Programming Language :: Python :: 3.9
Classifier: Programming Language :: Python :: 3.10
Classifier: License :: OSI Approved :: MIT License
Requires-Python: >=3.7.0
Requires-Dist: astroid (>=2.11)
Requires-Dist: charset-normalizer
Requires-Dist: pylint
Requires-Dist: pylint-guidelines-checker
